ai_tools/__init__.py
ai_tools/chatbot.py
ai_tools/drawing.py
ai_tools/main.py
ai_tools/setup_api_keys.py
usingai311-0.2.0.dist-info/METADATA
usingai311-0.2.0.dist-info/WHEEL
usingai311-0.2.0.dist-info/entry_points.txt
usingai311-0.2.0.dist-info/top_level.txt
usingai311-0.2.0.dist-info/RECORD
